{"cameraMode":{"drawMode":0,"name":"Shaded","section":"Shading Mode"},"sceneLighting":true,"audioPlay":false,"sceneViewState":{"m_AlwaysRefresh":false,"showFog":true,"showSkybox":true,"showFlares":true,"showImageEffects":true,"showParticleSystems":true,"showVisualEffectGraphs":true,"m_FxEnabled":true},"in2DMode":false,"pivot":{"x":368.52899169921877,"y":169.85208129882813,"z":52.02757263183594},"rotation":{"x":-0.17193900048732758,"y":-0.012712261639535427,"z":0.002220735652372241,"w":-0.9850379228591919},"size":354.2115783691406,"orthographic":false}